Westerlund/__init__.py
Westerlund/main.py
westerlund-0.1.0.dist-info/licenses/LICENSE
westerlund-0.1.0.dist-info/METADATA
westerlund-0.1.0.dist-info/WHEEL
westerlund-0.1.0.dist-info/top_level.txt
westerlund-0.1.0.dist-info/RECORD
