Metadata-Version: 2.4
Name: Westerlund
Version: 0.1.0
Summary: Westerlund: Westerlund ECM Panel Cointegration Test.
Author-email: Bosco Hung <bosco.hung@st-annes.ox.ac.uk>
Project-URL: Homepage, https://github.com/bosco-hung/WesterlundTest
Project-URL: Bug Tracker, https://github.com/bosco-hung/WesterlundTest/issues
Classifier: Programming Language :: Python :: 3
Classifier: License :: OSI Approved :: MIT License
Classifier: Operating System :: OS Independent
Classifier: Intended Audience :: Science/Research
Classifier: Intended Audience :: Education
Classifier: Topic :: Scientific/Engineering :: Information Analysis
Classifier: Topic :: Scientific/Engineering :: Mathematics
Classifier: Topic :: Sociology
Requires-Python: >=3.8
License-File: LICENSE
Requires-Dist: numpy>=1.20.0
Requires-Dist: pandas>=1.3.0
Requires-Dist: statsmodels>=0.13.0
Requires-Dist: scipy>=1.7.0
Requires-Dist: matplotlib>=3.4.0
Requires-Dist: seaborn>=0.11.0
Dynamic: license-file
